senti_c/__init__.py
senti_c/aspect_model_finetuning.py
senti_c/aspect_sentiment_analysis.py
senti_c/model_structure.py
senti_c/sentence_model_finetuning.py
senti_c/sentence_sentiment_analysis.py
senti_c/pretrained_model/__init__.py
senti_c/pretrained_model/chinese_aspect_model/__init__.py
senti_c/pretrained_model/chinese_sentence_model/__init__.py
senti_c/utils/__init__.py
senti_c/utils/aspect_processor.py
senti_c/utils/general.py
senti_c/utils/sentence_processor.py
senti_c-0.2.0.dist-info/METADATA
senti_c-0.2.0.dist-info/WHEEL
senti_c-0.2.0.dist-info/top_level.txt
senti_c-0.2.0.dist-info/RECORD
