Metadata-Version: 2.1
Name: senti-c
Version: 0.2.0
Summary: Traditional Chinese sentiment analysis tool based on BERT.
Home-page: https://github.com/hsinmin/senti_c
Author: Julie Tu and Hsin-min Lu
Author-email: luim@ntu.edu.tw
License: MIT
Keywords: traditional chinese,sentiment analysis,BERT,transformer,transfer learning
Platform: UNKNOWN
Classifier: Programming Language :: Python :: 3.8
Classifier: License :: OSI Approved :: MIT License
Classifier: Topic :: Software Development :: Build Tools
Requires-Python: >=3.7
Requires-Dist: pandas
Requires-Dist: scikit-learn
Requires-Dist: scipy (==1.4.1)
Requires-Dist: tensorflow (==2.2.0)
Requires-Dist: torch (<1.9.9,>1.0)
Requires-Dist: transformers (==2.11.0)
